paper_weaver/__init__.py
paper_weaver/__main__.py
paper_weaver/argparse.py
paper_weaver/bfs.py
paper_weaver/dataclass.py
paper_weaver/iface.py
paper_weaver/iface_a2p.py
paper_weaver/iface_init.py
paper_weaver/iface_link.py
paper_weaver/iface_p2a.py
paper_weaver/iface_p2c.py
paper_weaver/iface_p2r.py
paper_weaver/iface_p2v.py
paper_weaver/iface_v2p.py
paper_weaver/weaver_a2p2v.py
paper_weaver/cache/__init__.py
paper_weaver/cache/argparse.py
paper_weaver/cache/factory.py
paper_weaver/cache/identifier.py
paper_weaver/cache/impl.py
paper_weaver/cache/impl_a2p.py
paper_weaver/cache/impl_full.py
paper_weaver/cache/impl_link.py
paper_weaver/cache/impl_p2a.py
paper_weaver/cache/impl_p2c.py
paper_weaver/cache/impl_p2r.py
paper_weaver/cache/impl_p2v.py
paper_weaver/cache/impl_v2p.py
paper_weaver/cache/info_storage.py
paper_weaver/cache/link_storage.py
paper_weaver/cache/pending_storage.py
paper_weaver/cache/memory/__init__.py
paper_weaver/cache/memory/identifier.py
paper_weaver/cache/memory/info_storage.py
paper_weaver/cache/memory/link_storage.py
paper_weaver/cache/memory/pending_storage.py
paper_weaver/cache/redis/__init__.py
paper_weaver/cache/redis/identifier.py
paper_weaver/cache/redis/info_storage.py
paper_weaver/cache/redis/link_storage.py
paper_weaver/cache/redis/pending_storage.py
paper_weaver/datadst/__init__.py
paper_weaver/datadst/argparse.py
paper_weaver/datadst/neo4j/__init__.py
paper_weaver/datadst/neo4j/author.py
paper_weaver/datadst/neo4j/datadst.py
paper_weaver/datadst/neo4j/paper.py
paper_weaver/datadst/neo4j/utils.py
paper_weaver/datadst/neo4j/venue.py
paper_weaver/datasrc/__init__.py
paper_weaver/datasrc/argparse.py
paper_weaver/datasrc/cache.py
paper_weaver/datasrc/cache_impl.py
paper_weaver/datasrc/title_hash.py
paper_weaver/datasrc/arxiv/__init__.py
paper_weaver/datasrc/crossref/__init__.py
paper_weaver/datasrc/dblp/__init__.py
paper_weaver/datasrc/dblp/datasrc.py
paper_weaver/datasrc/dblp/person.py
paper_weaver/datasrc/dblp/record.py
paper_weaver-1.1.5.dist-info/METADATA
paper_weaver-1.1.5.dist-info/WHEEL
paper_weaver-1.1.5.dist-info/entry_points.txt
paper_weaver-1.1.5.dist-info/top_level.txt
paper_weaver-1.1.5.dist-info/RECORD
