Metadata-Version: 2.4
Name: paper-weaver
Version: 1.1.5
Summary: Weave academic paper data from various sources (DBLP, Semantic Scholar) into graph databases.
Author-email: yindaheng98 <yindaheng98@gmail.com>
License: MIT
Project-URL: Homepage, https://github.com/yindaheng98/PaperWeaver
Keywords: academic,paper,citation,dblp,semantic-scholar,neo4j,graph-database
Classifier: Programming Language :: Python :: 3
Classifier: Programming Language :: Python :: 3.10
Classifier: Programming Language :: Python :: 3.11
Classifier: Programming Language :: Python :: 3.12
Classifier: License :: OSI Approved :: MIT License
Classifier: Operating System :: OS Independent
Classifier: Topic :: Scientific/Engineering
Classifier: Topic :: Database
Requires-Python: >=3.10
Requires-Dist: aiohttp>=3.8.0
Requires-Dist: neo4j>=5.0.0
Requires-Dist: redis>=5.0.0
Requires-Dist: dblp-webxml-parser>=0.1.0
Provides-Extra: dev
Requires-Dist: pytest>=7.0.0; extra == "dev"
Requires-Dist: pytest-asyncio>=0.21.0; extra == "dev"
